[
  {
    "__type__": "cc.SpriteFrame",
    "content": {
      "name": "btn_single_luzhou",
      "texture": "b4HkDVH6pCNaWTAkbX+qpU",
      "rect": [
        0,
        0,
        362,
        217
      ],
      "offset": [
        0,
        0
      ],
      "originalSize": [
        362,
        217
      ],
      "capInsets": [
        0,
        0,
        0,
        0
      ]
    }
  },
  {
    "__type__": "cc.SpriteFrame",
    "content": {
      "name": "default_btn_disabled",
      "texture": "71VhFCTINJM6/Ky3oX9nBT",
      "rect": [
        0,
        0,
        40,
        40
      ],
      "offset": [
        0,
        0
      ],
      "originalSize": [
        40,
        40
      ],
      "capInsets": [
        12,
        12,
        12,
        12
      ]
    }
  },
  {
    "__type__": "cc.SpriteFrame",
    "content": {
      "name": "btn_single_classic",
      "texture": "0eqNnwF9FB1YoOC/UUdL9Z",
      "rect": [
        0,
        0,
        362,
        217
      ],
      "offset": [
        0,
        0
      ],
      "originalSize": [
        362,
        217
      ],
      "capInsets": [
        0,
        0,
        0,
        0
      ]
    }
  },
  {
    "__type__": "cc.SpriteFrame",
    "content": {
      "name": "bg_main_layer_background",
      "texture": "1cOO907RdHq6ADa0JsWJ+8",
      "rect": [
        0,
        0,
        1280,
        720
      ],
      "offset": [
        0,
        0
      ],
      "originalSize": [
        1280,
        720
      ],
      "capInsets": [
        0,
        0,
        0,
        0
      ]
    }
  },
  {
    "__type__": "cc.SpriteFrame",
    "content": {
      "name": "btn_single_fours",
      "texture": "83/+Y+ijBI5a+lZjmRriFQ",
      "rect": [
        0,
        0,
        362,
        217
      ],
      "offset": [
        0,
        0
      ],
      "originalSize": [
        362,
        217
      ],
      "capInsets": [
        0,
        0,
        0,
        0
      ]
    }
  },
  {
    "__type__": "cc.SpriteFrame",
    "content": {
      "name": "btn_single_fifteen",
      "texture": "a6KyjgaxZNorTa/iqTeZyI",
      "rect": [
        0,
        0,
        362,
        217
      ],
      "offset": [
        0,
        0
      ],
      "originalSize": [
        362,
        217
      ],
      "capInsets": [
        0,
        0,
        0,
        0
      ]
    }
  },
  {
    "__type__": "cc.SpriteFrame",
    "content": {
      "name": "btn_single_four",
      "texture": "e7khMAEoFJaLuRcPaHYhRM",
      "rect": [
        2,
        7,
        358,
        216
      ],
      "offset": [
        0,
        -3.5
      ],
      "originalSize": [
        362,
        223
      ],
      "capInsets": [
        0,
        0,
        0,
        0
      ]
    }
  },
  [
    {
      "__type__": "cc.Prefab",
      "_name": "singlegame",
      "data": {
        "__id__": 1
      }
    },
    {
      "__type__": "cc.Node",
      "_name": "singlegame",
      "_children": [
        {
          "__id__": 2
        },
        {
          "__id__": 3
        },
        {
          "__id__": 4
        },
        {
          "__id__": 5
        },
        {
          "__id__": 6
        },
        {
          "__id__": 7
        }
      ],
      "_level": 1,
      "_prefab": {
        "__type__": "cc.PrefabInfo",
        "root": {
          "__id__": 1
        },
        "asset": {
          "__uuid__": "e3tiQfjZ5Nt7TbbYtgDBFy"
        },
        "fileId": "50McQe+/JCXaKNYKfPTqGe"
      },
      "_contentSize": {
        "__type__": "cc.Size",
        "width": 1280,
        "height": 720
      },
      "_position": {
        "__type__": "cc.Vec3",
        "x": 640,
        "y": 360
      },
      "_scale": {
        "__type__": "cc.Vec3",
        "x": 1,
        "y": 1,
        "z": 1
      }
    },
    {
      "__type__": "cc.Node",
      "_name": "bg",
      "_parent": {
        "__id__": 1
      },
      "_level": 2,
      "_components": [
        {
          "__type__": "cc.Sprite",
          "node": {
            "__id__": 2
          },
          "_spriteFrame": {
            "__uuid__": "4ev1SK9G9CyrvBbDqmHupQ"
          }
        }
      ],
      "_prefab": {
        "__type__": "cc.PrefabInfo",
        "root": {
          "__id__": 1
        },
        "asset": {
          "__uuid__": "e3tiQfjZ5Nt7TbbYtgDBFy"
        },
        "fileId": "adQAxmyLpHxbINfKjKXDw2"
      },
      "_contentSize": {
        "__type__": "cc.Size",
        "width": 1280,
        "height": 720
      },
      "_scale": {
        "__type__": "cc.Vec3",
        "x": 1,
        "y": 1,
        "z": 1
      }
    },
    {
      "__type__": "cc.Node",
      "_name": "custombtn",
      "_parent": {
        "__id__": 1
      },
      "_level": 2,
      "_components": [
        {
          "__type__": "cc.Sprite",
          "node": {
            "__id__": 3
          },
          "_spriteFrame": {
            "__uuid__": "2cx6LppFpMt68vhXRA3LmL"
          },
          "_type": 1
        },
        {
          "__type__": "cc.Button",
          "node": {
            "__id__": 3
          },
          "_N$transition": 3,
          "transition": 3,
          "_N$normalColor": {
            "__type__": "cc.Color",
            "r": 255,
            "g": 255,
            "b": 255
          },
          "_N$pressedColor": {
            "__type__": "cc.Color",
            "r": 255,
            "g": 255,
            "b": 255
          },
          "pressedColor": {
            "__type__": "cc.Color",
            "r": 255,
            "g": 255,
            "b": 255
          },
          "_N$disabledColor": {
            "__type__": "cc.Color",
            "r": 255,
            "g": 255,
            "b": 255
          },
          "_N$normalSprite": {
            "__uuid__": "2cx6LppFpMt68vhXRA3LmL"
          },
          "_N$pressedSprite": {
            "__uuid__": "e97GVMl6JHh5Ml5qEDdSGa"
          },
          "pressedSprite": {
            "__uuid__": "e97GVMl6JHh5Ml5qEDdSGa"
          },
          "_N$hoverSprite": {
            "__uuid__": "f0BIwQ8D5Ml7nTNQbh1YlS"
          },
          "hoverSprite": {
            "__uuid__": "f0BIwQ8D5Ml7nTNQbh1YlS"
          },
          "_N$disabledSprite": {
            "__uuid__": "29FYIk+N1GYaeWH/q1NxQO"
          },
          "_N$target": {
            "__id__": 3
          }
        }
      ],
      "_prefab": {
        "__type__": "cc.PrefabInfo",
        "root": {
          "__id__": 1
        },
        "asset": {
          "__uuid__": "e3tiQfjZ5Nt7TbbYtgDBFy"
        },
        "fileId": "f4C71X0ShOEJJgmbGoH+M+"
      },
      "_contentSize": {
        "__type__": "cc.Size",
        "width": 362,
        "height": 217
      },
      "_position": {
        "__type__": "cc.Vec3",
        "x": -372,
        "y": 61
      },
      "_scale": {
        "__type__": "cc.Vec3",
        "x": 1,
        "y": 1,
        "z": 1
      }
    },
    {
      "__type__": "cc.Node",
      "_name": "fiftenbtn",
      "_parent": {
        "__id__": 1
      },
      "_level": 2,
      "_components": [
        {
          "__type__": "cc.Sprite",
          "node": {
            "__id__": 4
          },
          "_spriteFrame": {
            "__uuid__": "88fKjjT3FIkZArphX2j2+Z"
          },
          "_type": 1
        },
        {
          "__type__": "cc.Button",
          "node": {
            "__id__": 4
          },
          "_N$transition": 3,
          "transition": 3,
          "_N$normalColor": {
            "__type__": "cc.Color",
            "r": 255,
            "g": 255,
            "b": 255
          },
          "_N$pressedColor": {
            "__type__": "cc.Color",
            "r": 255,
            "g": 255,
            "b": 255
          },
          "pressedColor": {
            "__type__": "cc.Color",
            "r": 255,
            "g": 255,
            "b": 255
          },
          "_N$disabledColor": {
            "__type__": "cc.Color",
            "r": 255,
            "g": 255,
            "b": 255
          },
          "_N$normalSprite": {
            "__uuid__": "2cx6LppFpMt68vhXRA3LmL"
          },
          "_N$pressedSprite": {
            "__uuid__": "e97GVMl6JHh5Ml5qEDdSGa"
          },
          "pressedSprite": {
            "__uuid__": "e97GVMl6JHh5Ml5qEDdSGa"
          },
          "_N$hoverSprite": {
            "__uuid__": "f0BIwQ8D5Ml7nTNQbh1YlS"
          },
          "hoverSprite": {
            "__uuid__": "f0BIwQ8D5Ml7nTNQbh1YlS"
          },
          "_N$disabledSprite": {
            "__uuid__": "29FYIk+N1GYaeWH/q1NxQO"
          },
          "_N$target": {
            "__id__": 4
          }
        }
      ],
      "_prefab": {
        "__type__": "cc.PrefabInfo",
        "root": {
          "__id__": 1
        },
        "asset": {
          "__uuid__": "e3tiQfjZ5Nt7TbbYtgDBFy"
        },
        "fileId": "ccYMo4JSxB06W9zlw+1cpq"
      },
      "_contentSize": {
        "__type__": "cc.Size",
        "width": 362,
        "height": 217
      },
      "_position": {
        "__type__": "cc.Vec3",
        "x": -2,
        "y": 61
      },
      "_scale": {
        "__type__": "cc.Vec3",
        "x": 1,
        "y": 1,
        "z": 1
      }
    },
    {
      "__type__": "cc.Node",
      "_name": "luzhoubtn",
      "_parent": {
        "__id__": 1
      },
      "_level": 2,
      "_components": [
        {
          "__type__": "cc.Sprite",
          "node": {
            "__id__": 5
          },
          "_spriteFrame": {
            "__uuid__": "02f8IcbDNGPIkJIS8O29TG"
          },
          "_type": 1
        },
        {
          "__type__": "cc.Button",
          "node": {
            "__id__": 5
          },
          "_N$transition": 3,
          "transition": 3,
          "_N$normalColor": {
            "__type__": "cc.Color",
            "r": 255,
            "g": 255,
            "b": 255
          },
          "_N$pressedColor": {
            "__type__": "cc.Color",
            "r": 255,
            "g": 255,
            "b": 255
          },
          "pressedColor": {
            "__type__": "cc.Color",
            "r": 255,
            "g": 255,
            "b": 255
          },
          "_N$disabledColor": {
            "__type__": "cc.Color",
            "r": 255,
            "g": 255,
            "b": 255
          },
          "_N$normalSprite": {
            "__uuid__": "2cx6LppFpMt68vhXRA3LmL"
          },
          "_N$pressedSprite": {
            "__uuid__": "e97GVMl6JHh5Ml5qEDdSGa"
          },
          "pressedSprite": {
            "__uuid__": "e97GVMl6JHh5Ml5qEDdSGa"
          },
          "_N$hoverSprite": {
            "__uuid__": "f0BIwQ8D5Ml7nTNQbh1YlS"
          },
          "hoverSprite": {
            "__uuid__": "f0BIwQ8D5Ml7nTNQbh1YlS"
          },
          "_N$disabledSprite": {
            "__uuid__": "29FYIk+N1GYaeWH/q1NxQO"
          },
          "_N$target": {
            "__id__": 5
          }
        }
      ],
      "_prefab": {
        "__type__": "cc.PrefabInfo",
        "root": {
          "__id__": 1
        },
        "asset": {
          "__uuid__": "e3tiQfjZ5Nt7TbbYtgDBFy"
        },
        "fileId": "baaIh8Jc5OMKHFNeVB+0iT"
      },
      "_contentSize": {
        "__type__": "cc.Size",
        "width": 362,
        "height": 217
      },
      "_position": {
        "__type__": "cc.Vec3",
        "x": 370,
        "y": 57
      },
      "_scale": {
        "__type__": "cc.Vec3",
        "x": 1,
        "y": 1,
        "z": 1
      }
    },
    {
      "__type__": "cc.Node",
      "_name": "fourbtn",
      "_parent": {
        "__id__": 1
      },
      "_level": 2,
      "_components": [
        {
          "__type__": "cc.Sprite",
          "node": {
            "__id__": 6
          },
          "_spriteFrame": {
            "__uuid__": "8dCMl+vlBJ+LCAw1Dv6X6N"
          },
          "_type": 1
        },
        {
          "__type__": "cc.Button",
          "node": {
            "__id__": 6
          },
          "_N$transition": 3,
          "transition": 3,
          "_N$normalColor": {
            "__type__": "cc.Color",
            "r": 255,
            "g": 255,
            "b": 255
          },
          "_N$pressedColor": {
            "__type__": "cc.Color",
            "r": 255,
            "g": 255,
            "b": 255
          },
          "pressedColor": {
            "__type__": "cc.Color",
            "r": 255,
            "g": 255,
            "b": 255
          },
          "_N$disabledColor": {
            "__type__": "cc.Color",
            "r": 255,
            "g": 255,
            "b": 255
          },
          "_N$normalSprite": {
            "__uuid__": "2cx6LppFpMt68vhXRA3LmL"
          },
          "_N$pressedSprite": {
            "__uuid__": "e97GVMl6JHh5Ml5qEDdSGa"
          },
          "pressedSprite": {
            "__uuid__": "e97GVMl6JHh5Ml5qEDdSGa"
          },
          "_N$hoverSprite": {
            "__uuid__": "f0BIwQ8D5Ml7nTNQbh1YlS"
          },
          "hoverSprite": {
            "__uuid__": "f0BIwQ8D5Ml7nTNQbh1YlS"
          },
          "_N$disabledSprite": {
            "__uuid__": "29FYIk+N1GYaeWH/q1NxQO"
          },
          "_N$target": {
            "__id__": 6
          }
        }
      ],
      "_prefab": {
        "__type__": "cc.PrefabInfo",
        "root": {
          "__id__": 1
        },
        "asset": {
          "__uuid__": "e3tiQfjZ5Nt7TbbYtgDBFy"
        },
        "fileId": "36LKOO6oFK+I5VxLMkHNmL"
      },
      "_contentSize": {
        "__type__": "cc.Size",
        "width": 358,
        "height": 216
      },
      "_position": {
        "__type__": "cc.Vec3",
        "x": -197,
        "y": -172
      },
      "_scale": {
        "__type__": "cc.Vec3",
        "x": 1,
        "y": 1,
        "z": 1
      }
    },
    {
      "__type__": "cc.Node",
      "_name": "foursbtn",
      "_parent": {
        "__id__": 1
      },
      "_level": 2,
      "_components": [
        {
          "__type__": "cc.Sprite",
          "node": {
            "__id__": 7
          },
          "_spriteFrame": {
            "__uuid__": "5dayoP/shLJ4J4c0rb+EE6"
          },
          "_type": 1
        },
        {
          "__type__": "cc.Button",
          "node": {
            "__id__": 7
          },
          "_N$transition": 3,
          "transition": 3,
          "_N$normalColor": {
            "__type__": "cc.Color",
            "r": 255,
            "g": 255,
            "b": 255
          },
          "_N$pressedColor": {
            "__type__": "cc.Color",
            "r": 255,
            "g": 255,
            "b": 255
          },
          "pressedColor": {
            "__type__": "cc.Color",
            "r": 255,
            "g": 255,
            "b": 255
          },
          "_N$disabledColor": {
            "__type__": "cc.Color",
            "r": 255,
            "g": 255,
            "b": 255
          },
          "_N$normalSprite": {
            "__uuid__": "2cx6LppFpMt68vhXRA3LmL"
          },
          "_N$pressedSprite": {
            "__uuid__": "e97GVMl6JHh5Ml5qEDdSGa"
          },
          "pressedSprite": {
            "__uuid__": "e97GVMl6JHh5Ml5qEDdSGa"
          },
          "_N$hoverSprite": {
            "__uuid__": "f0BIwQ8D5Ml7nTNQbh1YlS"
          },
          "hoverSprite": {
            "__uuid__": "f0BIwQ8D5Ml7nTNQbh1YlS"
          },
          "_N$disabledSprite": {
            "__uuid__": "29FYIk+N1GYaeWH/q1NxQO"
          },
          "_N$target": {
            "__id__": 7
          }
        }
      ],
      "_prefab": {
        "__type__": "cc.PrefabInfo",
        "root": {
          "__id__": 1
        },
        "asset": {
          "__uuid__": "e3tiQfjZ5Nt7TbbYtgDBFy"
        },
        "fileId": "1edhnNiYlAcaAIizc9Enpc"
      },
      "_contentSize": {
        "__type__": "cc.Size",
        "width": 362,
        "height": 217
      },
      "_position": {
        "__type__": "cc.Vec3",
        "x": 177.5,
        "y": -172
      },
      "_scale": {
        "__type__": "cc.Vec3",
        "x": 1,
        "y": 1,
        "z": 1
      }
    }
  ],
  {
    "__type__": "cc.SpriteFrame",
    "content": {
      "name": "default_btn_pressed",
      "texture": "b4P/PCArtIdIH38t6mlw8Y",
      "rect": [
        0,
        0,
        40,
        40
      ],
      "offset": [
        0,
        0
      ],
      "originalSize": [
        40,
        40
      ],
      "capInsets": [
        12,
        12,
        12,
        12
      ]
    }
  },
  {
    "__type__": "cc.SpriteFrame",
    "content": {
      "name": "default_btn_normal",
      "texture": "e8Ueib+qJEhL6mXAHdnwbi",
      "rect": [
        0,
        0,
        40,
        40
      ],
      "offset": [
        0,
        0
      ],
      "originalSize": [
        40,
        40
      ],
      "capInsets": [
        12,
        12,
        12,
        12
      ]
    }
  }
]